{
  "groups": [
    {
      "id": "group_0",
      "name": "Q704",
      "columns": [
        "Q704r1",
        "Q704r2",
        "Q704r3"
      ]
    },
    {
      "id": "group_1",
      "name": "Q701",
      "columns": [
        "Q701r1",
        "Q701r2",
        "Q701r3",
        "Q701r4",
        "Q701r5",
        "Q701r6",
        "Q701r7",
        "Q701r8",
        "Q701r9",
        "Q701r10",
        "Q701r11",
        "Q701r12",
        "Q701r13",
        "Q701r14",
        "Q701r15",
        "Q701r16",
        "Q701r17",
        "Q701r996",
        "Q701r997"
      ]
    },
    {
      "id": "group_2",
      "name": "Q702",
      "columns": [
        "Q702r1",
        "Q702r2",
        "Q702r3",
        "Q702r4",
        "Q702r5",
        "Q702r6",
        "Q702r7",
        "Q702r8",
        "Q702r9",
        "Q702r10",
        "Q702r11",
        "Q702r12",
        "Q702r13",
        "Q702r14",
        "Q702r15",
        "Q702r16",
        "Q702r17",
        "Q702r18",
        "Q702r19",
        "Q702r20",
        "Q702r21",
        "Q702r22",
        "Q702r23",
        "Q702r24",
        "Q702r25",
        "Q702r26",
        "Q702r996",
        "Q702r997"
      ]
    },
    {
      "id": "group_3",
      "name": "Q703",
      "columns": [
        "Q703r1",
        "Q703r2",
        "Q703r3",
        "Q703r4",
        "Q703r5",
        "Q703r6"
      ]
    },
    {
      "id": "group_4",
      "name": "Q202",
      "columns": [
        "Q202r1",
        "Q202r2",
        "Q202r3",
        "Q202r4",
        "Q202r5",
        "Q202r6",
        "Q202r7",
        "Q202r8",
        "Q202r9",
        "Q202r10",
        "Q202r11",
        "Q202r12",
        "Q202r996"
      ]
    },
    {
      "id": "group_5",
      "name": "Q202_rec",
      "columns": [
        "Q202_rec_r1",
        "Q202_rec_r2",
        "Q202_rec_r3",
        "Q202_rec_r4",
        "Q202_rec_r5",
        "Q202_rec_r6",
        "Q202_rec_r7",
        "Q202_rec_r8",
        "Q202_rec_r9",
        "Q202_rec_r10",
        "Q202_rec_r11",
        "Q202_rec_r12",
        "Q202_rec_r996"
      ]
    },
    {
      "id": "group_6",
      "name": "Q204",
      "columns": [
        "Q204r1",
        "Q204r2",
        "Q204r3",
        "Q204r4",
        "Q204r5",
        "Q204r6",
        "Q204r7",
        "Q204r8",
        "Q204r9",
        "Q204r996"
      ]
    },
    {
      "id": "group_7",
      "name": "Q204_rec",
      "columns": [
        "Q204_rec_r1",
        "Q204_rec_r2",
        "Q204_rec_r3",
        "Q204_rec_r4",
        "Q204_rec_r5",
        "Q204_rec_r6",
        "Q204_rec_r7",
        "Q204_rec_r8",
        "Q204_rec_r9",
        "Q204_rec_r996"
      ]
    },
    {
      "id": "group_8",
      "name": "Q205",
      "columns": [
        "Q205r1",
        "Q205r2",
        "Q205r3",
        "Q205r4",
        "Q205r996"
      ]
    },
    {
      "id": "group_9",
      "name": "Q207",
      "columns": [
        "Q207r1",
        "Q207r2",
        "Q207r3",
        "Q207r4",
        "Q207r5",
        "Q207r6",
        "Q207r7",
        "Q207r8",
        "Q207r9",
        "Q207r996"
      ]
    },
    {
      "id": "group_10",
      "name": "hQ208",
      "columns": [
        "hQ208r1",
        "hQ208r2",
        "hQ208r3",
        "hQ208r4",
        "hQ208r6"
      ]
    },
    {
      "id": "group_11",
      "name": "Q801",
      "columns": [
        "Q801r1",
        "Q801r2",
        "Q801r3",
        "Q801r4",
        "Q801r5",
        "Q801r6",
        "Q801r7",
        "Q801r8",
        "Q801r9",
        "Q801r10",
        "Q801r11",
        "Q801r12",
        "Q801r13",
        "Q801r14",
        "Q801r15",
        "Q801r16",
        "Q801r17",
        "Q801r18",
        "Q801r19",
        "Q801r20",
        "Q801r21",
        "Q801r22",
        "Q801r23",
        "Q801r27",
        "Q801r28",
        "Q801r996"
      ]
    },
    {
      "id": "group_12",
      "name": "Q802",
      "columns": [
        "Q802r1",
        "Q802r2",
        "Q802r3",
        "Q802r4",
        "Q802r5",
        "Q802r6",
        "Q802r7",
        "Q802r8",
        "Q802r9",
        "Q802r10",
        "Q802r11",
        "Q802r12",
        "Q802r13",
        "Q802r14",
        "Q802r15",
        "Q802r16",
        "Q802r17",
        "Q802r18",
        "Q802r19",
        "Q802r20",
        "Q802r21",
        "Q802r22",
        "Q802r23",
        "Q802r27",
        "Q802r28",
        "Q802r996"
      ]
    },
    {
      "id": "group_13",
      "name": "Q803",
      "columns": [
        "Q803r1",
        "Q803r2",
        "Q803r3",
        "Q803r4"
      ]
    },
    {
      "id": "group_14",
      "name": "Q804",
      "columns": [
        "Q804r1",
        "Q804r2",
        "Q804r3",
        "Q804r4",
        "Q804r5",
        "Q804r6",
        "Q804r7",
        "Q804r8",
        "Q804r9",
        "Q804r10",
        "Q804r11",
        "Q804r12",
        "Q804r13",
        "Q804r14",
        "Q804r15",
        "Q804r16",
        "Q804r17",
        "Q804r18",
        "Q804r19",
        "Q804r20",
        "Q804r21",
        "Q804r22",
        "Q804r23",
        "Q804r27",
        "Q804r28",
        "Q804r996"
      ]
    },
    {
      "id": "group_15",
      "name": "Q303",
      "columns": [
        "Q303r1",
        "Q303r2",
        "Q303r3",
        "Q303r4",
        "Q303r5",
        "Q303r6",
        "Q303r7",
        "Q303r8",
        "Q303r9",
        "Q303r996"
      ]
    },
    {
      "id": "group_16",
      "name": "Q304",
      "columns": [
        "Q304r1",
        "Q304r2"
      ]
    },
    {
      "id": "group_17",
      "name": "Q306",
      "columns": [
        "Q306r1",
        "Q306r2",
        "Q306r4",
        "Q306r5",
        "Q306r6",
        "Q306r7",
        "Q306r8",
        "Q306r9",
        "Q306r10",
        "Q306r11",
        "Q306r12",
        "Q306r13",
        "Q306r997",
        "Q306r998"
      ]
    },
    {
      "id": "group_18",
      "name": "Q307",
      "columns": [
        "Q307r1",
        "Q307r2",
        "Q307r3",
        "Q307r5",
        "Q307r6",
        "Q307r7",
        "Q307r8",
        "Q307r9",
        "Q307r10",
        "Q307r11",
        "Q307r12",
        "Q307r13",
        "Q307r14",
        "Q307r15",
        "Q307r16",
        "Q307r17",
        "Q307r18",
        "Q307r20",
        "Q307r21",
        "Q307r22",
        "Q307r23",
        "Q307r24",
        "Q307r25",
        "Q307r996"
      ]
    },
    {
      "id": "group_19",
      "name": "Q403",
      "columns": [
        "Q403r1",
        "Q403r3",
        "Q403r4",
        "Q403r5",
        "Q403r6",
        "Q403r7",
        "Q403r8",
        "Q403r996"
      ]
    },
    {
      "id": "group_20",
      "name": "Q406",
      "columns": [
        "Q406r1",
        "Q406r2",
        "Q406r3",
        "Q406r4",
        "Q406r5",
        "Q406r6",
        "Q406r7",
        "Q406r8",
        "Q406r9",
        "Q406r10",
        "Q406r997",
        "Q406r998"
      ]
    },
    {
      "id": "group_21",
      "name": "Q407",
      "columns": [
        "Q407r1",
        "Q407r2",
        "Q407r3",
        "Q407r4",
        "Q407r5",
        "Q407r6",
        "Q407r7",
        "Q407r8",
        "Q407r9",
        "Q407r10",
        "Q407r11",
        "Q407r12",
        "Q407r13",
        "Q407r15",
        "Q407r16",
        "Q407r17",
        "Q407r18",
        "Q407r19",
        "Q407r20",
        "Q407r21",
        "Q407r22",
        "Q407r996"
      ]
    },
    {
      "id": "group_22",
      "name": "Q501",
      "columns": [
        "Q501r1c1",
        "Q501r1c2",
        "Q501r1c3",
        "Q501r1c4",
        "Q501r1c5",
        "Q501r2c1",
        "Q501r2c2",
        "Q501r2c3",
        "Q501r2c4",
        "Q501r2c5",
        "Q501r3c1",
        "Q501r3c2",
        "Q501r3c3",
        "Q501r3c4",
        "Q501r3c5",
        "Q501r4c1",
        "Q501r4c2",
        "Q501r4c3",
        "Q501r4c4",
        "Q501r4c5",
        "Q501r5c1",
        "Q501r5c2",
        "Q501r5c3",
        "Q501r5c4",
        "Q501r5c5",
        "Q501r6c1",
        "Q501r6c2",
        "Q501r6c3",
        "Q501r6c4",
        "Q501r6c5",
        "Q501r7c1",
        "Q501r7c2",
        "Q501r7c3",
        "Q501r7c4",
        "Q501r7c5",
        "Q501r8c1",
        "Q501r8c2",
        "Q501r8c3",
        "Q501r8c4",
        "Q501r8c5"
      ]
    },
    {
      "id": "group_23",
      "name": "Q504",
      "columns": [
        "Q504r1",
        "Q504r2"
      ]
    },
    {
      "id": "group_24",
      "name": "Q505",
      "columns": [
        "Q505r1",
        "Q505r2",
        "Q505r3",
        "Q505r4",
        "Q505r5",
        "Q505r6",
        "Q505r7",
        "Q505r8",
        "Q505r9",
        "Q505r10",
        "Q505r997",
        "Q505r998"
      ]
    },
    {
      "id": "group_25",
      "name": "Q506",
      "columns": [
        "Q506r1",
        "Q506r2",
        "Q506r3",
        "Q506r4",
        "Q506r5",
        "Q506r6",
        "Q506r7",
        "Q506r8",
        "Q506r9",
        "Q506r10",
        "Q506r11",
        "Q506r12",
        "Q506r13",
        "Q506r996"
      ]
    },
    {
      "id": "group_26",
      "name": "Q601",
      "columns": [
        "Q601c1",
        "Q601c2",
        "Q601c3"
      ]
    },
    {
      "id": "group_27",
      "name": "Q901",
      "columns": [
        "Q901r1",
        "Q901r2",
        "Q901r3",
        "Q901r4",
        "Q901r5",
        "Q901r6",
        "Q901r7",
        "Q901r8",
        "Q901r9",
        "Q901r10",
        "Q901r11",
        "Q901r12",
        "Q901r13",
        "Q901r14",
        "Q901r15",
        "Q901r16",
        "Q901r17",
        "Q901r18",
        "Q901r19",
        "Q901r20",
        "Q901r21",
        "Q901r22",
        "Q901r23",
        "Q901r24",
        "Q901r25",
        "Q901r26",
        "Q901r27",
        "Q901r28",
        "Q901r29",
        "Q901r30",
        "Q901r31"
      ]
    },
    {
      "id": "group_28",
      "name": "Q901_rec",
      "columns": [
        "Q901_rec_r1",
        "Q901_rec_r2",
        "Q901_rec_r3",
        "Q901_rec_r4",
        "Q901_rec_r5",
        "Q901_rec_r6",
        "Q901_rec_r7",
        "Q901_rec_r8",
        "Q901_rec_r9",
        "Q901_rec_r10",
        "Q901_rec_r11",
        "Q901_rec_r12",
        "Q901_rec_r13",
        "Q901_rec_r14",
        "Q901_rec_r15",
        "Q901_rec_r16",
        "Q901_rec_r17",
        "Q901_rec_r18",
        "Q901_rec_r19",
        "Q901_rec_r20",
        "Q901_rec_r21",
        "Q901_rec_r22",
        "Q901_rec_r23",
        "Q901_rec_r24",
        "Q901_rec_r25",
        "Q901_rec_r26",
        "Q901_rec_r27",
        "Q901_rec_r28",
        "Q901_rec_r29",
        "Q901_rec_r30",
        "Q901_rec_r31"
      ]
    },
    {
      "id": "group_29",
      "name": "Q902",
      "columns": [
        "Q902r1",
        "Q902r2",
        "Q902r3",
        "Q902r4",
        "Q902r5",
        "Q902r6",
        "Q902r7",
        "Q902r8",
        "Q902r9",
        "Q902r10",
        "Q902r11",
        "Q902r995",
        "Q902r12",
        "Q902r13",
        "Q902r14",
        "Q902r15",
        "Q902r16",
        "Q902r17",
        "Q902r18",
        "Q902r996"
      ]
    },
    {
      "id": "group_30",
      "name": "Q907",
      "columns": [
        "Q907r1",
        "Q907r2",
        "Q907r3",
        "Q907r4",
        "Q907r5",
        "Q907r6",
        "Q907r7",
        "Q907r8",
        "Q907r996"
      ]
    }
  ]
}